[
    {
        "_id": ObjectId("657bbb49675e5c32a2b8af72"),
        "item": "journal",
        "qty": 25,
        "size": { "h": 14, "w": 21, "uom": "cm" },
        "status": "A"
    },
    {
        "_id": ObjectId("657bbb49675e5c32a2b8af73"),
        "item": "notebook",
        "qty": 50,
        "size": { "h": 8.5, "w": 11, "uom": "in" },
        "status": "A"
    },
    {
        "_id": ObjectId("657bbb49675e5c32a2b8af74"),
        "item": "paper",
        "qty": 100,
        "size": { "h": 8.5, "w": 11, "uom": "in" },
        "status": "D"
    },
    {
        "_id": ObjectId("657bbb49675e5c32a2b8af75"),
        "item": "planner",
        "qty": 75,
        "size": { "h": 22.85, "w": 30, "uom": "cm" },
        "status": "D"
    },
    {
        "_id": ObjectId("657bbb49675e5c32a2b8af76"),
        "item": "postcard",
        "qty": 45,
        "size": { "h": 10, "w": 15.25, "uom": "cm" },
        "status": "A"
    }
]